Metadata-Version: 1.0
Name: jair-matrices
Version: 1.0
Summary: Matrix basic operation
Home-page: UNKNOWN
Author: UNKNOWN
Author-email: UNKNOWN
License: UNKNOWN
Platform: UNKNOWN
